LatestEarthquake/__init__.py
r2_LatestEarthquake-0.2.dist-info/LICENSE
r2_LatestEarthquake-0.2.dist-info/METADATA
r2_LatestEarthquake-0.2.dist-info/WHEEL
r2_LatestEarthquake-0.2.dist-info/top_level.txt
r2_LatestEarthquake-0.2.dist-info/RECORD
