Metadata-Version: 2.1
Name: r2-LatestEarthquake
Version: 0.2
Summary: This package will get the latest earthquake from BMKG
Home-page: https://github.com/ricky-blip/LatestEarthquakeIndonesia.git
Author: Ricky Rinaldy
Author-email: ricky.rinaldy77@gmail.com
License: UNKNOWN
Project-URL: About Author, https://bit.ly/3ABmegZ
Platform: UNKNOWN
Classifier: Programming Language :: Python :: 3
Classifier: License :: OSI Approved :: GNU General Public License v3 (GPLv3)
Classifier: Operating System :: OS Independent
Classifier: Development Status :: 5 - Production/Stable
Requires-Python: >=3.6
License-File: LICENSE
